<annotation>
	<folder>JPEGImages</folder>
	<filename>000161.jpg</filename>
	<path>D:\fish_data\VOCdevkit_fish\VOC2012\JPEGImages\000161.jpg</path>
	<source>
		<database>Unknown</database>
	</source>
	<size>
		<width>516</width>
		<height>462</height>
		<depth>3</depth>
	</size>
	<segmented>0</segmented>
	<object>
		<name>fish</name>
		<pose>Unspecified</pose>
		<truncated>0</truncated>
		<difficult>0</difficult>
		<bndbox>
			<xmin>427</xmin>
			<ymin>309</ymin>
			<xmax>506</xmax>
			<ymax>414</ymax>
		</bndbox>
	</object>
</annotation>
